pyjaws/__init__.py
pyjaws/api/__init__.py
pyjaws/api/base.py
pyjaws/api/jobs.py
pyjaws/api/runtime.py
pyjaws/api/tasks.py
pyjaws/api/templates/workflow.j2
pyjaws/api/templates/macros/cluster.j2
pyjaws/api/templates/macros/task.j2
pyjaws/client/__init__.py
pyjaws/client/entrypoint.py
pyjaws-0.1.7.dist-info/METADATA
pyjaws-0.1.7.dist-info/WHEEL
pyjaws-0.1.7.dist-info/entry_points.txt
pyjaws-0.1.7.dist-info/top_level.txt
pyjaws-0.1.7.dist-info/RECORD
