Metadata-Version: 2.1
Name: pyjaws
Version: 0.1.7
Requires-Dist: click
Requires-Dist: python-rapidjson ==1.10
Requires-Dist: pydantic ==1.10.5
Requires-Dist: Jinja2 ==3.1.2
Requires-Dist: networkx
Requires-Dist: GitPython ==3.1.35
Requires-Dist: requests <2.30.0
Requires-Dist: urllib3 <2
Requires-Dist: matplotlib
Requires-Dist: databricks-sdk ==0.8.0
